etherscan/__init__.py
etherscan/http_client.py
etherscan/http_resp.py
etherscan/ratelimiter.py
etherscan_v2-0.0.3.dist-info/METADATA
etherscan_v2-0.0.3.dist-info/WHEEL
etherscan_v2-0.0.3.dist-info/top_level.txt
etherscan_v2-0.0.3.dist-info/RECORD
