Metadata-Version: 2.4
Name: etherscan-v2
Version: 0.0.3
Home-page: 
Requires-Dist: httpx
Dynamic: description
Dynamic: description-content-type
Dynamic: requires-dist
